torchrtm/__init__.py
torchrtm/data_loader.py
torchrtm/atmosphere/__init__.py
torchrtm/atmosphere/smac.py
torchrtm/canopy/__init__.py
torchrtm/canopy/hotspot.py
torchrtm/canopy/lidf.py
torchrtm/canopy/sail.py
torchrtm/canopy/sail_geometry.py
torchrtm/canopy/sail_radiative.py
torchrtm/canopy/suits.py
torchrtm/data/CoefMat.csv
torchrtm/data/__init__.py
torchrtm/data/all_para.csv
torchrtm/data/check_info_scrap.py
torchrtm/data/data_prospectd.csv
torchrtm/data/data_prospectpro.csv
torchrtm/data/rtm_soil.csv
torchrtm/data/sensor_information/LANDSAT4-TM.pkl
torchrtm/data/sensor_information/LANDSAT5-TM.pkl
torchrtm/data/sensor_information/LANDSAT7-ETM.pkl
torchrtm/data/sensor_information/LANDSAT8-OLI.pkl
torchrtm/data/sensor_information/Sentinel2A-MSI.pkl
torchrtm/data/sensor_information/Sentinel2B-MSI.pkl
torchrtm/data/sensor_information/Sentinel3A-OLCI.pkl
torchrtm/data/sensor_information/Sentinel3B-OLCI.pkl
torchrtm/data/sensor_information/TerraAqua-MODIS.pkl
torchrtm/leaf/__init__.py
torchrtm/leaf/fresnel.py
torchrtm/leaf/prospect.py
torchrtm/models/__init__.py
torchrtm/models/models.py
torchrtm/retrival/__init__.py
torchrtm/retrival/fastLUT.py
torchrtm/retrival/fastNN.py
torchrtm/utils/__init__.py
torchrtm/utils/math_torch.py
torchrtm/utils/spectradataset.py
torchrtm/utils/torch_utils.py
torchrtm/utils/torchlut.py
torchrtm-1.4.3.dist-info/LICENSE
torchrtm-1.4.3.dist-info/METADATA
torchrtm-1.4.3.dist-info/WHEEL
torchrtm-1.4.3.dist-info/top_level.txt
torchrtm-1.4.3.dist-info/RECORD
